Workbook

Sheet Instructions
A1: Loan Risk Policy Simulator
A3: PURPOSE: Test 'what if we only approved loans up to a certain risk level?' and see the effect on default rate and profit.
A5: HOW TO USE
A6: 1. Go to the 'Policy_Simulator' sheet.
A7: 2. Change the YELLOW cells (max grade approved, or number of risk deciles approved).
A8: 3. Read the results below each input - they update automatically.
A10: COLOUR LEGEND
A11: Blue text = data aggregated from the Python analysis (hard-coded inputs)
A12: Black text = Excel formulas (do not overwrite)
A13: Yellow fill = cells YOU can change
A15: DATA SOURCE: 50,000 synthetic loans (see project README). Profit = total payments received - loan amount.
A16: Risk deciles come from the logistic-regression model (decile 1 = safest, 10 = riskiest).
A17: Example row: set Max grade = 'E' -> grades F and G are declined; compare default rate and profit vs approving everyone.

Sheet Policy_Simulator
A1: Policy Simulator - what if we tightened approvals?
A2: Change the yellow cells. Results recalculate automatically.
A4: SCENARIO 1: Approve only loans up to a maximum lender grade
A5: Max grade approved (A-G) | B5: G
A6: Grade index (helper) | B6: =MATCH(B5,Grade_Summary!$A$5:$A$11,0)-1 -> 6
A8: Loans approved | B8: =SUMIFS(Grade_Summary!$C$5:$C$11,Grade_Summary!$B$5:$B$11,"<="&B6) -> 50000
A9: % of applicants approved | B9: =B8/Grade_Summary!$C$12 -> 1
A10: Defaults among approved | B10: =SUMIFS(Grade_Summary!$E$5:$E$11,Grade_Summary!$B$5:$B$11,"<="&B6) -> 7721
A11: Default rate (approved book) | B11: =IFERROR(B10/B8,0) -> 0.15442
A12: Default rate (approve everyone) | B12: =Grade_Summary!$G$12 -> 0.15442
A13: Total profit (approved book) | B13: =SUMIFS(Grade_Summary!$F$5:$F$11,Grade_Summary!$B$5:$B$11,"<="&B6) -> 87106815
A14: Total profit (approve everyone) | B14: =Grade_Summary!$F$12 -> 87106815
A15: PROFIT CHANGE vs approve-everyone | B15: =B13-B14 -> 0
A18: SCENARIO 2: Approve only the safest N risk deciles (model score)
A19: Safest deciles approved (1-10) | B19: 9
A20: Loans approved | B20: =SUMIFS(Risk_Deciles!$B$5:$B$14,Risk_Deciles!$A$5:$A$14,"<="&B19) -> 45000
A21: % of applicants approved | B21: =B20/Risk_Deciles!$B$15 -> 0.9
A22: Defaults among approved | B22: =SUMIFS(Risk_Deciles!$D$5:$D$14,Risk_Deciles!$A$5:$A$14,"<="&B19) -> 5730
A23: Default rate (approved book) | B23: =IFERROR(B22/B20,0) -> 0.12733333
A24: Default rate (approve everyone) | B24: =Risk_Deciles!$F$15 -> 0.15442
A25: Total profit (approved book) | B25: =SUMIFS(Risk_Deciles!$E$5:$E$14,Risk_Deciles!$A$5:$A$14,"<="&B19) -> 88333249
A26: Total profit (approve everyone) | B26: =Risk_Deciles!$E$15 -> 87106815
A27: PROFIT CHANGE vs approve-everyone | B27: =B25-B26 -> 1226434.1
A30: How to read it: try deciles = 9 (decline the riskiest 10%) vs 8 or 7. Profit usually rises first, then falls once you start rejecting good, interest-paying loans.

Sheet Grade_Summary
A1: Portfolio by lender grade
A4: Grade | B4: Grade Index | C4: Loans | D4: Loan Amount ($) | E4: Defaults | F4: Profit ($) | G4: Default Rate | H4: Profit per Loan ($) | I4: Share of Loans
A5: A | B5: 0 | C5: 6508 | D5: 109896475 | E5: 391 | F5: 8937510.8 | G5: =IFERROR(E5/C5,0) -> 0.060079902 | H5: =IFERROR(F5/C5,0) -> 1373.3114 | I5: =C5/$C$12 -> 0.13016
A6: B | B6: 1 | C6: 9549 | D6: 161151325 | E6: 848 | F6: 17138624 | G6: =IFERROR(E6/C6,0) -> 0.08880511 | H6: =IFERROR(F6/C6,0) -> 1794.8083 | I6: =C6/$C$12 -> 0.19098
A7: C | B7: 2 | C7: 10817 | D7: 181461175 | E7: 1296 | F7: 22069895 | G7: =IFERROR(E7/C7,0) -> 0.11981141 | H7: =IFERROR(F7/C7,0) -> 2040.2972 | I7: =C7/$C$12 -> 0.21634
A8: D | B8: 3 | C8: 10450 | D8: 174215425 | E8: 1694 | F8: 22658220 | G8: =IFERROR(E8/C8,0) -> 0.16210526 | H8: =IFERROR(F8/C8,0) -> 2168.2507 | I8: =C8/$C$12 -> 0.209
A9: E | B9: 4 | C9: 6223 | D9: 103638425 | E9: 1393 | F9: 11145776 | G9: =IFERROR(E9/C9,0) -> 0.22384702 | H9: =IFERROR(F9/C9,0) -> 1791.0616 | I9: =C9/$C$12 -> 0.12446
A10: F | B10: 5 | C10: 3729 | D10: 62645900 | E10: 1123 | F10: 3752896.2 | G10: =IFERROR(E10/C10,0) -> 0.30115312 | H10: =IFERROR(F10/C10,0) -> 1006.4082 | I10: =C10/$C$12 -> 0.07458
A11: G | B11: 6 | C11: 2724 | D11: 45663825 | E11: 976 | F11: 1403892.6 | G11: =IFERROR(E11/C11,0) -> 0.35829662 | H11: =IFERROR(F11/C11,0) -> 515.37906 | I11: =C11/$C$12 -> 0.05448
A12: Total | C12: =SUM(C5:C11) -> 50000 | D12: =SUM(D5:D11) -> 838672550 | E12: =SUM(E5:E11) -> 7721 | F12: =SUM(F5:F11) -> 87106815 | G12: =IFERROR(E12/C12,0) -> 0.15442 | H12: =IFERROR(F12/C12,0) -> 1742.1363 | I12: =SUM(I5:I11) -> 1

Sheet Risk_Deciles
A1: Portfolio by model risk decile
A4: Risk Decile (1=safest) | B4: Loans | C4: Loan Amount ($) | D4: Defaults | E4: Profit ($) | F4: Default Rate | G4: Profit per Loan ($)
A5: 1 | B5: 5000 | C5: 71805175 | D5: 175 | E5: 8498198.1 | F5: =IFERROR(D5/B5,0) -> 0.035 | G5: =IFERROR(E5/B5,0) -> 1699.6396
A6: 2 | B6: 5000 | C6: 74555150 | D6: 287 | E6: 9246075.1 | F6: =IFERROR(D6/B6,0) -> 0.0574 | G6: =IFERROR(E6/B6,0) -> 1849.215
A7: 3 | B7: 5000 | C7: 78390850 | D7: 366 | E7: 9972808.4 | F7: =IFERROR(D7/B7,0) -> 0.0732 | G7: =IFERROR(E7/B7,0) -> 1994.5617
A8: 4 | B8: 5000 | C8: 80738600 | D8: 478 | E8: 10413645 | F8: =IFERROR(D8/B8,0) -> 0.0956 | G8: =IFERROR(E8/B8,0) -> 2082.7291
A9: 5 | B9: 5000 | C9: 82141050 | D9: 574 | E9: 11071237 | F9: =IFERROR(D9/B9,0) -> 0.1148 | G9: =IFERROR(E9/B9,0) -> 2214.2475
A10: 6 | B10: 5000 | C10: 84286925 | D10: 658 | E10: 11508931 | F10: =IFERROR(D10/B10,0) -> 0.1316 | G10: =IFERROR(E10/B10,0) -> 2301.7862
A11: 7 | B11: 5000 | C11: 86869900 | D11: 839 | E11: 10303308 | F11: =IFERROR(D11/B11,0) -> 0.1678 | G11: =IFERROR(E11/B11,0) -> 2060.6616
A12: 8 | B12: 5000 | C12: 88668200 | D12: 1034 | E12: 9738508.6 | F12: =IFERROR(D12/B12,0) -> 0.2068 | G12: =IFERROR(E12/B12,0) -> 1947.7017
A13: 9 | B13: 5000 | C13: 91824225 | D13: 1319 | E13: 7580536.7 | F13: =IFERROR(D13/B13,0) -> 0.2638 | G13: =IFERROR(E13/B13,0) -> 1516.1073
A14: 10 | B14: 5000 | C14: 99392475 | D14: 1991 | E14: -1226434.1 | F14: =IFERROR(D14/B14,0) -> 0.3982 | G14: =IFERROR(E14/B14,0) -> -245.28682
A15: Total | B15: =SUM(B5:B14) -> 50000 | C15: =SUM(C5:C14) -> 838672550 | D15: =SUM(D5:D14) -> 7721 | E15: =SUM(E5:E14) -> 87106815 | F15: =IFERROR(D15/B15,0) -> 0.15442 | G15: =IFERROR(E15/B15,0) -> 1742.1363
